sgipupdate/__init__.py
sgipupdate/cli.py
sgipupdate/sgipupdate.py
sgipupdate-0.1.0.dist-info/LICENSE
sgipupdate-0.1.0.dist-info/METADATA
sgipupdate-0.1.0.dist-info/WHEEL
sgipupdate-0.1.0.dist-info/entry_points.txt
sgipupdate-0.1.0.dist-info/top_level.txt
sgipupdate-0.1.0.dist-info/RECORD
