Metadata-Version: 2.1
Name: sgipupdate
Version: 0.1.0
Summary: Python CLI to update a security group with the current public IP address
Home-page: https://github.com/cvockrodt/sgipupdate
Author: Casey Vockrodt
Author-email: casey.vockrodt@gmail.com
License: MIT license
Platform: any
Classifier: Development Status :: 2 - Pre-Alpha
Classifier: Intended Audience :: Developers
Classifier: License :: OSI Approved :: MIT License
Classifier: Natural Language :: English
Classifier: Programming Language :: Python :: 3
Classifier: Programming Language :: Python :: 3.5
Classifier: Programming Language :: Python :: 3.6
Classifier: Programming Language :: Python :: 3.7
Classifier: Programming Language :: Python :: 3.8
Requires-Python: >=3.5
Requires-Dist: boto3
Requires-Dist: requests
Requires-Dist: click
Requires-Dist: click-config-file
